pykour/__init__.py
pykour/app.py
pykour/cli.py
pykour/config.py
pykour/db/__init__.py
pykour/db/connection.py
pykour/db/pool.py
pykour/exceptions.py
pykour/globals.py
pykour/internal/__init__.py
pykour/internal/handler/__init__.py
pykour/internal/handler/request.py
pykour/internal/handler/response.py
pykour/logging.py
pykour/middleware/__init__.py
pykour/middleware/base.py
pykour/middleware/gzip.py
pykour/middleware/uuid.py
pykour/openapi/__init__.py
pykour/openapi/endpoint.py
pykour/pykour.py
pykour/request.py
pykour/response.py
pykour/router.py
pykour/schema.py
pykour/testing.py
pykour/types.py
pykour/url.py
pykour/util.py
pykour/validator.py
pykour-0.3.0.dist-info/LICENSE
pykour-0.3.0.dist-info/METADATA
pykour-0.3.0.dist-info/WHEEL
pykour-0.3.0.dist-info/entry_points.txt
pykour-0.3.0.dist-info/RECORD
