Metadata-Version: 2.1
Name: pykour
Version: 0.3.0
Summary: Pykour is modern, fast, and easy to use REST framework for Python.
Author: Takashi Yamashina
Author-email: takashi.yamashina@gmail.com
Requires-Python: >=3.9
Classifier: Programming Language :: Python :: 3
Classifier: Programming Language :: Python :: 3.9
Classifier: Programming Language :: Python :: 3.10
Classifier: Programming Language :: Python :: 3.11
Classifier: Programming Language :: Python :: 3.12
Requires-Dist: colorama (>=0.4.6,<0.5.0)
Requires-Dist: pyyaml (>=6.0,<7.0)
Requires-Dist: uvicorn[standard] (>=0.30,<0.31)
Requires-Dist: watchdog (>=4.0,<5.0)
